{"skey": "ruzg9R7oi_3AHoWHbKVSuA", "clon": null, "lon": 13.33581, "cd": 2.0, "image_url": "https://d1cuyjsrcm0gby.cloudfront.net/imHi6djzZU1YXC3DYVa9sg/", "location": "Rankestra\u00dfe, Berlin", "key": "imHi6djzZU1YXC3DYVa9sg", "lat": 52.50419, "clat": null, "ca": 85.9715270996094, "map_image_versions": [{"url": "https://d1cuyjsrcm0gby.cloudfront.net/imHi6djzZU1YXC3DYVa9sg/thumb-320.jpg", "name": "thumb-320", "filename": "thumb-320.jpg"}, {"url": "https://d1cuyjsrcm0gby.cloudfront.net/imHi6djzZU1YXC3DYVa9sg/thumb-640.jpg", "name": "thumb-640", "filename": "thumb-640.jpg"}, {"url": "https://d1cuyjsrcm0gby.cloudfront.net/imHi6djzZU1YXC3DYVa9sg/thumb-1024.jpg", "name": "thumb-1024", "filename": "thumb-1024.jpg"}, {"url": "https://d1cuyjsrcm0gby.cloudfront.net/imHi6djzZU1YXC3DYVa9sg/thumb-2048.jpg", "name": "thumb-2048", "filename": "thumb-2048.jpg"}]}